lightlemma/__init__.py
lightlemma/lemmatizer.py
lightlemma/stemmer.py
lightlemma/tokenizer.py
lightlemma/data/irregular_forms.json
lightlemma-0.1.5.dist-info/METADATA
lightlemma-0.1.5.dist-info/WHEEL
lightlemma-0.1.5.dist-info/licenses/LICENSE
lightlemma-0.1.5.dist-info/RECORD
